setup.py
gbin/__init__.py
gbin/cli.py
gbin/gbin.py
gbin/utils.py
gbin.egg-info/PKG-INFO
gbin.egg-info/SOURCES.txt
gbin.egg-info/dependency_links.txt
gbin.egg-info/entry_points.txt
gbin.egg-info/requires.txt
gbin.egg-info/top_level.txt