Metadata-Version: 1.1
Name: gbin
Version: 0.3.0
Summary: a git based command discoverer and executor
Home-page: https://github.com/pnegahdar/gbin
Author: Parham Negahdar
Author-email: pnegahdar@gmail.com
License: MIT
Keywords: management commands git inenv gbin discovery cli python
Platform: UNKNOWN
Classifier: Development Status :: 4 - Beta
Classifier: Intended Audience :: Developers
Classifier: License :: OSI Approved :: MIT License
Classifier: Natural Language :: English
Classifier: Operating System :: Unix
Classifier: Programming Language :: Python :: 2.7
Classifier: Operating System :: OS Independent
